pysamosa-1.0.0.dist-info/LICENSE
pysamosa-1.0.0.dist-info/top_level.txt
pysamosa-1.0.0.dist-info/RECORD
pysamosa-1.0.0.dist-info/METADATA
pysamosa-1.0.0.dist-info/WHEEL
pysamosa/pysamosa.py
pysamosa/dist2coast.py
pysamosa/main_coral_paper.py
pysamosa/settings.py
pysamosa/data_access.py
pysamosa/main_s6jtex.py
pysamosa/main_s6.py
pysamosa/main_s6jtex_raw_vs_rmc.py
pysamosa/qual_flag_estimator.py
pysamosa/retracker_processor.py
pysamosa/retracker_helpers.py
pysamosa/montecarlo_simulator.py
pysamosa/settings_manager.py
pysamosa/luts_samosa.pickle
pysamosa/model.py
pysamosa/l1b_simulator.py
pysamosa/common_types.py
pysamosa/model_helpers.pyx
pysamosa/simple_logger.py
pysamosa/main_cs.py
pysamosa/version.py
pysamosa/main_s3.py
pysamosa/utils.py
pysamosa/rip.py
pysamosa/leading_edge_detector.py
pysamosa/model_helpers.cpython-310-x86_64-linux-gnu.so
pysamosa/download_aux_data.py
pysamosa/retracker.py
pysamosa/__init__.py
pysamosa/conf_params.py
pysamosa/main_coastalffsar.py
