Metadata-Version: 2.1
Name: pysamosa
Version: 1.0.0
Summary: PySAMOSA is a software framework for processing open ocean and coastal waveforms from SAR satellite altimetry to measure sea surface heights, wave heights, and wind speed for the oceans and inland water bodies. Satellite altimetry is a space-borne remote sensing technique used for Earth observation.
Home-page: https://github.com/floschl/pysamosa
Author: Florian Schlembach
Author-email: florian.schlembach@tum.de
License: GNU Lesser General Public License v3 or later (LGPLv3+)
Keywords: satellite altimetry retracking samosa+ samosa coastal open ocean sentinel esasar altimetry ff-sar fully focused
Classifier: Development Status :: 4 - Beta
Classifier: Intended Audience :: Developers
Classifier: License :: OSI Approved :: GNU Lesser General Public License v3 or later (LGPLv3+)
Classifier: Natural Language :: English
Classifier: Programming Language :: Python :: 3
Classifier: Programming Language :: Python :: 3.8
Classifier: Programming Language :: Python :: 3.9
Classifier: Programming Language :: Python :: 3.10
Classifier: Programming Language :: Python :: 3.11
Requires-Python: >=3.8
License-File: LICENSE
Requires-Dist: cython >0.29
Requires-Dist: xarray >=2023.1
Requires-Dist: netCDF4 >1.6.0
Requires-Dist: h5netcdf >=1.1
Requires-Dist: numpy >1.24
Requires-Dist: scipy >1.10
Requires-Dist: pandas >1.5
Requires-Dist: pydantic >2.0
Requires-Dist: tqdm >4.64
Requires-Dist: requests >2.28.1
Requires-Dist: matplotlib >3.5
Requires-Dist: bokeh >3.1
Requires-Dist: astropy >5.0
